wws_74hc165.py
woolseyworkshop_circuitpython_74hc165-1.0.0.dist-info/LICENSE
woolseyworkshop_circuitpython_74hc165-1.0.0.dist-info/METADATA
woolseyworkshop_circuitpython_74hc165-1.0.0.dist-info/WHEEL
woolseyworkshop_circuitpython_74hc165-1.0.0.dist-info/top_level.txt
woolseyworkshop_circuitpython_74hc165-1.0.0.dist-info/RECORD
