Metadata-Version: 2.1
Name: woolseyworkshop-circuitpython-74hc165
Version: 1.0.0
Summary: CircuitPython driver for 74HC165 shift register.
Author-email: Woolsey Workshop <support@woolseyworkshop.com>
License: MIT
Project-URL: Homepage, https://github.com/WoolseyWorkshop/WoolseyWorkshop_CircuitPython_74HC165
Keywords: adafruit,blinka,woolsey,shift,register,74hc165,hardware,micropython,circuitpython
Classifier: Intended Audience :: Developers
Classifier: Topic :: Software Development :: Libraries
Classifier: Topic :: Software Development :: Embedded Systems
Classifier: Topic :: System :: Hardware
Classifier: License :: OSI Approved :: MIT License
Classifier: Programming Language :: Python :: 3
License-File: LICENSE
Requires-Dist: Adafruit-Blinka
Requires-Dist: adafruit-circuitpython-busdevice
Requires-Dist: adafruit-circuitpython-typing
Provides-Extra: optional
